{
  "Serbia": [
    {
      "Name": "Bravo FM radio",
      "Genre": "Zabavna",
      "Stream": "http:\/\/streaming.orion.rs:8030\/;",
      "Logo": "https:\/\/epg.serbianforum.org\/radio\/bravosr.png",
      "Site": "http:\/\/www.bravofm.net\/"
    }
  ],
  "Croatia": [
    {
      "Name": "Bravo Radio",
      "Genre": "Live",
      "Stream": "http:\/\/c5.hostingcentar.com:8059\/;",
      "Logo": "http:\/\/streaming.br.hr\/stream\/noimageavailable.jpg",
      "Site": "https:\/\/br.hr\/"
    },
    {
      "Name": "Bravo Rock",
      "Genre": "Rock",
      "Stream": "http:\/\/c5.hostingcentar.com:8348\/;",
      "Logo": "http:\/\/streaming.br.hr\/stream\/noimageavailable.jpg",
      "Site": "https:\/\/br.hr\/"
    },
    {
      "Name": "Bravo balade",
      "Genre": "Balade",
      "Stream": "http:\/\/c5.hostingcentar.com:8360\/;",
      "Logo": "http:\/\/streaming.br.hr\/stream\/noimageavailable.jpg",
      "Site": "https:\/\/br.hr\/"
    },
    {
      "Name": "Bravo Pop",
      "Genre": "Pop",
      "Stream": "http:\/\/c5.hostingcentar.com:8354\/;",
      "Logo": "http:\/\/streaming.br.hr\/stream\/noimageavailable.jpg",
      "Site": "https:\/\/br.hr\/"
    },
    {
      "Name": "Bravo Feel",
      "Genre": "Feel",
      "Stream": "http:\/\/c5.hostingcentar.com:8366\/;",
      "Logo": "http:\/\/streaming.br.hr\/stream\/noimageavailable.jpg",
      "Site": "https:\/\/br.hr\/"
    }
  ],
  "Macedonia": [
    {
      "Name": "Bravo radio",
      "Genre": "Blues, Jazz",
      "Stream": "http:\/\/80.77.157.10:8000\/;*.mp3",
      "Logo": "https:\/\/epg.serbianforum.org\/radio\/bravo.jpg",
      "Site": "http:\/\/radiobravo.com.mk\/"
    }
  ]
}